odoo8_addon_website_sale_unsaleable_options-8.0.1.0.0.99.dev11-py2.7-nspkg.pth
odoo8_addon_website_sale_unsaleable_options-8.0.1.0.0.99.dev11.dist-info/DESCRIPTION.rst
odoo8_addon_website_sale_unsaleable_options-8.0.1.0.0.99.dev11.dist-info/METADATA
odoo8_addon_website_sale_unsaleable_options-8.0.1.0.0.99.dev11.dist-info/RECORD
odoo8_addon_website_sale_unsaleable_options-8.0.1.0.0.99.dev11.dist-info/WHEEL
odoo8_addon_website_sale_unsaleable_options-8.0.1.0.0.99.dev11.dist-info/metadata.json
odoo8_addon_website_sale_unsaleable_options-8.0.1.0.0.99.dev11.dist-info/namespace_packages.txt
odoo8_addon_website_sale_unsaleable_options-8.0.1.0.0.99.dev11.dist-info/top_level.txt
odoo_addons/website_sale_unsaleable_options/README.rst
odoo_addons/website_sale_unsaleable_options/__init__.py
odoo_addons/website_sale_unsaleable_options/__openerp__.py
odoo_addons/website_sale_unsaleable_options/controllers/__init__.py
odoo_addons/website_sale_unsaleable_options/controllers/main.py
odoo_addons/website_sale_unsaleable_options/i18n/de.po
odoo_addons/website_sale_unsaleable_options/i18n/el_GR.po
odoo_addons/website_sale_unsaleable_options/i18n/es.po
odoo_addons/website_sale_unsaleable_options/i18n/eu.po
odoo_addons/website_sale_unsaleable_options/i18n/fr.po
odoo_addons/website_sale_unsaleable_options/i18n/it.po
odoo_addons/website_sale_unsaleable_options/i18n/pt_BR.po
odoo_addons/website_sale_unsaleable_options/i18n/sl.po
odoo_addons/website_sale_unsaleable_options/i18n/tr.po
odoo_addons/website_sale_unsaleable_options/i18n/website_sale_unsaleable_options.pot
odoo_addons/website_sale_unsaleable_options/static/description/icon.png
odoo_addons/website_sale_unsaleable_options/views/templates.xml
